steganer-1.1.0_post4.dist-info/METADATA
steganer-1.1.0_post4.dist-info/WHEEL
steganer/__init__.py
steganer/ffi.py
steganer/native.so
steganer-1.1.0_post4.dist-info/RECORD
