Metadata-Version: 2.1
Name: steganer
Version: 1.1.0-post4
Summary: Library to hide a file inside another... or to recover it.
Home-Page: https://github.com/dante-signal31/steganer
Author: dante-signal31 <dante.signal31@gmail.com>
Author-Email: dante-signal31 <dante.signal31@gmail.com>
License: BSD-3-Clause
